pyweibo/__init__.py
pyweibo/auth.py
pyweibo/client.py
pyweibo/reader.py
pyweibo/token.py
pyweibo-0.1.2.dist-info/LICENSE.txt
pyweibo-0.1.2.dist-info/METADATA
pyweibo-0.1.2.dist-info/WHEEL
pyweibo-0.1.2.dist-info/top_level.txt
pyweibo-0.1.2.dist-info/RECORD
