Metadata-Version: 2.1
Name: pyweibo
Version: 0.1.2
Summary: Python SDK for Weibo API
Home-page: https://github.com/Thesharing/pyweibo
Author: Thesharing
Author-email: 
License: MIT
Platform: UNKNOWN
Classifier: Development Status :: 4 - Beta
Classifier: Environment :: Console
Classifier: Intended Audience :: Developers
Classifier: Operating System :: OS Independent
Classifier: Programming Language :: Python
Classifier: Topic :: Software Development
Requires-Python: >=3.4, <4
Requires-Dist: spiderutil (>=0.1.6)
